setup.py
gc_pysensu.egg-info/PKG-INFO
gc_pysensu.egg-info/SOURCES.txt
gc_pysensu.egg-info/dependency_links.txt
gc_pysensu.egg-info/requires.txt
gc_pysensu.egg-info/top_level.txt
pysensu/__init__.py
pysensu/pysensu.py