Metadata-Version: 1.0
Name: gc-pysensu
Version: 0.6
Summary: Utilities for working with Sensu
Home-page: https://github.com/kdaniels/pysensu
Author: K. Daniels
Author-email: kd@gc.io
License: UNKNOWN
Platform: UNKNOWN
